moesifdjango/__init__.py
moesifdjango/block_response_buffer.py
moesifdjango/client_ip.py
moesifdjango/event_mapper.py
moesifdjango/governance_rule_response.py
moesifdjango/governance_rules.py
moesifdjango/http_response_catcher.py
moesifdjango/job_scheduler.py
moesifdjango/logger_helper.py
moesifdjango/masks.py
moesifdjango/middleware.py
moesifdjango/middleware_pre19.py
moesifdjango/moesif_gov.py
moesifdjango/parse_body.py
moesifdjango/update_companies.py
moesifdjango/update_subscriptions.py
moesifdjango/update_users.py
moesifdjango-2.3.13.dist-info/licenses/LICENSE
moesifdjango-2.3.13.dist-info/METADATA
moesifdjango-2.3.13.dist-info/WHEEL
moesifdjango-2.3.13.dist-info/top_level.txt
moesifdjango-2.3.13.dist-info/RECORD
